{
 "aggregate_function_based_on": "amount",
 "creation": "2022-11-10 13:32:04.561603",
 "docstatus": 0,
 "doctype": "Number Card",
 "document_type": "Tickets Sold",
 "dynamic_filters_json": "[]",
 "filters_json": "[[\"Tickets Sold\",\"transaction_date\",\"Timespan\",\"today\",false]]",
 "function": "Sum",
 "idx": 0,
 "is_public": 0,
 "is_standard": 1,
 "label": "Today Ticket Sold Revenue",
 "modified": "2022-11-10 13:32:17.053688",
 "modified_by": "Administrator",
 "module": "E Ticket Management",
 "name": "Today Ticket Sold Revenue",
 "owner": "Administrator",
 "parent_document_type": "",
 "report_field": "total_qty",
 "report_function": "Sum",
 "report_name": "POS Sale Summary Report",
 "show_percentage_stats": 0,
 "stats_time_interval": "Daily",
 "type": "Document Type"
}